{
  "config": "{\"version\":\"5.59\",\"themeCollection\":{\"baseTheme\":{\"name\":\"CY24SU10\",\"version\":\"5.60\",\"type\":2}},\"activeSectionIndex\":0,\"defaultDrillFilterOtherVisuals\":true,\"linguisticSchemaSyncVersion\":2,\"settings\":{\"useNewFilterPaneExperience\":true,\"allowChangeFilterTypes\":true,\"useStylableVisualContainerHeader\":true,\"queryLimitOption\":6,\"useEnhancedTooltips\":true,\"exportDataMode\":1,\"useDefaultAggregateDisplayName\":true},\"objects\":{\"section\":[{\"properties\":{\"verticalAlignment\":{\"expr\":{\"Literal\":{\"Value\":\"'Top'\"}}}}}]}}",
  "layoutOptimization": 0,
  "resourcePackages": [
    {
      "resourcePackage": {
        "disabled": false,
        "items": [
          {
            "name": "CY24SU10",
            "path": "BaseThemes/CY24SU10.json",
            "type": 202
          }
        ],
        "name": "SharedResources",
        "type": 2
      }
    }
  ],
  "sections": [
    {
      "config": "{\"objects\":{\"background\":[{\"properties\":{\"image\":{\"image\":{\"name\":{\"expr\":{\"Literal\":{\"Value\":\"''\"}}},\"url\":{\"expr\":{\"Literal\":{\"Value\":\"''\"}}}}},\"transparency\":{\"expr\":{\"Literal\":{\"Value\":\"0D\"}}}}}]}}",
      "displayName": "Página 1",
      "displayOption": 1,
      "filters": "[]",
      "height": 720.00,
      "name": "464126b828b9c859bba4",
      "visualContainers": [
        {
          "config": "{\"name\":\"b182d28aee32ff730d4a\",\"layouts\":[{\"id\":0,\"position\":{\"x\":732.9219600725953,\"y\":0,\"z\":0,\"width\":547.0780399274047,\"height\":248.56624319419237,\"tabOrder\":0}}],\"singleVisual\":{\"visualType\":\"lineChart\",\"projections\":{\"Y\":[{\"queryRef\":\"Avg(cotacoes.Cotacao)\"}],\"Category\":[{\"queryRef\":\"calendario.Data\",\"active\":true}]},\"prototypeQuery\":{\"Version\":2,\"From\":[{\"Name\":\"c\",\"Entity\":\"cotacoes\",\"Type\":0},{\"Name\":\"c1\",\"Entity\":\"calendario\",\"Type\":0}],\"Select\":[{\"Aggregation\":{\"Expression\":{\"Column\":{\"Expression\":{\"SourceRef\":{\"Source\":\"c\"}},\"Property\":\"Cotacao\"}},\"Function\":1},\"Name\":\"Avg(cotacoes.Cotacao)\",\"NativeReferenceName\":\"Média de Cotacao\"},{\"Column\":{\"Expression\":{\"SourceRef\":{\"Source\":\"c1\"}},\"Property\":\"Data\"},\"Name\":\"calendario.Data\",\"NativeReferenceName\":\"Data\"}],\"OrderBy\":[{\"Direction\":1,\"Expression\":{\"Column\":{\"Expression\":{\"SourceRef\":{\"Source\":\"c1\"}},\"Property\":\"Data\"}}}]},\"drillFilterOtherVisuals\":true,\"hasDefaultSort\":true,\"objects\":{\"labels\":[{\"properties\":{\"show\":{\"expr\":{\"Literal\":{\"Value\":\"false\"}}}}}]}}}",
          "filters": "[]",
          "height": 248.57,
          "width": 547.08,
          "x": 732.92,
          "y": 0.00,
          "z": 0.00
        },
        {
          "config": "{\"name\":\"fd01d50c4c4a3d433f05\",\"layouts\":[{\"id\":0,\"position\":{\"x\":0,\"y\":0,\"z\":1000,\"width\":219.52813067150635,\"height\":403.04900181488205,\"tabOrder\":1000}}],\"singleVisual\":{\"visualType\":\"slicer\",\"projections\":{\"Values\":[{\"queryRef\":\"moedas.Moeda\",\"active\":true}]},\"prototypeQuery\":{\"Version\":2,\"From\":[{\"Name\":\"m\",\"Entity\":\"moedas\",\"Type\":0}],\"Select\":[{\"Column\":{\"Expression\":{\"SourceRef\":{\"Source\":\"m\"}},\"Property\":\"Moeda\"},\"Name\":\"moedas.Moeda\",\"NativeReferenceName\":\"Moeda\"}]},\"drillFilterOtherVisuals\":true,\"objects\":{\"data\":[{\"properties\":{\"mode\":{\"expr\":{\"Literal\":{\"Value\":\"'Basic'\"}}}}}],\"general\":[{\"properties\":{\"filter\":{\"filter\":{\"Version\":2,\"From\":[{\"Name\":\"m\",\"Entity\":\"moedas\",\"Type\":0}],\"Where\":[{\"Condition\":{\"In\":{\"Expressions\":[{\"Column\":{\"Expression\":{\"SourceRef\":{\"Source\":\"m\"}},\"Property\":\"Moeda\"}}],\"Values\":[[{\"Literal\":{\"Value\":\"'USD'\"}}]]}}}]}}}}]}}}",
          "filters": "[]",
          "height": 403.05,
          "width": 219.53,
          "x": 0.00,
          "y": 0.00,
          "z": 1000.00
        }
      ],
      "width": 1280.00
    }
  ]
}